fastapi_dataclass_battery/__init__.py
fastapi_dataclass_battery/dataclasses.py
fastapi_dataclass_battery/fastapi.py
fastapi_dataclass_battery-0.0.1.dist-info/LICENSE.md
fastapi_dataclass_battery-0.0.1.dist-info/METADATA
fastapi_dataclass_battery-0.0.1.dist-info/WHEEL
fastapi_dataclass_battery-0.0.1.dist-info/top_level.txt
fastapi_dataclass_battery-0.0.1.dist-info/RECORD
